{
"812": {"x":620, "y":262, "connections": ["376"]},
"376": {"x":589, "y":315, "connections": ["813"]},
"813": {"x":596, "y":302, "connections": ["391"]},
"391": {"x":669, "y":250, "connections": ["713"]},
"713": {"x":668, "y":250, "connections": ["193"]},
"193": {"x":803, "y":285, "connections": ["585"]},
"585": {"x":799, "y":284, "connections": ["61"]},
"61": {"x":777, "y":368, "connections": ["591"]},
"591": {"x":798, "y":290, "connections": ["430"]},
"430": {"x":793, "y":289, "connections": []}
}